odoo8_addon_purchase_order_import-8.0.1.0.0.99.dev10-nspkg.pth
odoo_addons/purchase_order_import/README.rst
odoo_addons/purchase_order_import/__init__.py
odoo_addons/purchase_order_import/__openerp__.py
odoo_addons/purchase_order_import/i18n/fr.po
odoo_addons/purchase_order_import/i18n/pt_BR.po
odoo_addons/purchase_order_import/i18n/purchase_order_import.pot
odoo_addons/purchase_order_import/static/description/icon.png
odoo_addons/purchase_order_import/views/purchase.xml
odoo_addons/purchase_order_import/wizard/__init__.py
odoo_addons/purchase_order_import/wizard/purchase_order_import.py
odoo_addons/purchase_order_import/wizard/purchase_order_import_view.xml
odoo8_addon_purchase_order_import-8.0.1.0.0.99.dev10.dist-info/METADATA
odoo8_addon_purchase_order_import-8.0.1.0.0.99.dev10.dist-info/WHEEL
odoo8_addon_purchase_order_import-8.0.1.0.0.99.dev10.dist-info/namespace_packages.txt
odoo8_addon_purchase_order_import-8.0.1.0.0.99.dev10.dist-info/top_level.txt
odoo8_addon_purchase_order_import-8.0.1.0.0.99.dev10.dist-info/RECORD
